{
  "eyebrow": "দর্শনীয় স্থান",
  "title": "মক্কা ও মদীনার দর্শনীয় স্থান ও স্থাপনা",
  "description": "মক্কা মুকাররামা এবং মদীনা মুনাওওয়ারায় পরিদর্শন করা যেতে পারে এমন সবচেয়ে গুরুত্বপূর্ণ ঐতিহাসিক স্থানগুলো সম্পর্কে জানুন, শরয়ী পরিদর্শনের বিধান সহ।",
  "cities": {
    "all": "সব",
    "makkah": "মক্কা মুকাররামা",
    "madinah": "মদীনা মুনাওওয়ারা"
  },
  "labels": {
    "viewDetails": "বিস্তারিত দেখুন ←",
    "distanceFromHaram": "হারাম থেকে দূরত্ব",
    "bestTimeToVisit": "পরিদর্শনের সেরা সময়",
    "city": "শহর",
    "backToAll": "← সকল দর্শনীয় স্থানে ফিরুন",
    "historyTitle": "ঐতিহাসিক সংক্ষিপ্ত বিবরণ",
    "visitHowTitle": "কীভাবে পরিদর্শন করবেন",
    "notFoundTitle": "দর্শনীয় স্থান পাওয়া যায়নি",
    "notFoundDesc": "অনুরোধকৃত দর্শনীয় স্থান খুঁজে পাওয়া যায়নি।",
    "notFoundBack": "দর্শনীয় স্থানে ফিরুন"
  },
  "items": {
    "a1": {
      "name": "জাবালে নূর এবং গারে হেরা",
      "city": "মক্কা মুকাররামা",
      "description": "যে পর্বতে নবী ﷺ রিসালাতের আগে ইবাদত করতেন, এবং এতে গারে হেরা আছে যেখানে প্রথম ওহী নাযিল হয়েছিল।",
      "tip": "এর পরিদর্শন উমরাহর মানাসিকের অংশ নয়, বরং এটি একটি ঐতিহাসিক পরিদর্শন যা যে চায় তার জন্য জায়েজ শিক্ষা নেওয়ার জন্য, আরোহণে শারীরিক পরিশ্রম বিবেচনা করে।",
      "distance": "হারাম থেকে প্রায় ৪ কিমি",
      "history": "জাবালে নূরের উপরে গারে হেরায় নবী ﷺ রিসালাতের আগে ইবাদত করতেন, এবং সেখানে তাঁর উপর প্রথম ওহী নাযিল হয় আল্লাহর বাণী দ্বারা: ﴿اقْرَأْ بِاسْمِ رَبِّكَ الَّذِي خَلَقَ﴾, যার মাধ্যমে ইসলামের রিসালাত শুরু হয়।",
      "howToVisit": "দর্শনার্থীরা একটি খুব খাড়া পাথরের সিঁড়ি বেয়ে উঠেন যা প্রায় এক ঘণ্টা থেকে দেড় ঘণ্টা লাগে, এবং পর্যাপ্ত পানি সাথে নেওয়া এবং দুপুরের গরম সময় এড়ানোর পরামর্শ দেওয়া হয়।",
      "bestTime": "সূর্যের তাপ এড়াতে এবং সরু সিঁড়ির ভিড় এড়াতে সকাল বেলা বা আসরের পরে।"
    },
    "a2": {
      "name": "জাবালে সাওর",
      "city": "মক্কা মুকাররামা",
      "description": "যে পর্বতে নবী ﷺ এবং তাঁর সাহাবী আবু বকর সিদ্দীক রাদিয়াল্লাহু আনহু মদীনায় হিজরতের সময় লুকিয়েছিলেন।",
      "tip": "এতে আরোহণ কষ্টকর এবং কয়েক ঘণ্টা সময় নেয়, এবং এটি একটি ঐচ্ছিক পরিদর্শন যার উমরাহর মানাসিকের সাথে কোনো সম্পর্ক নেই।",
      "distance": "হারামের দক্ষিণে প্রায় ৬ কিমি",
      "history": "গারে সাওরে নবী ﷺ এবং তাঁর সাহাবী আবু বকর সিদ্দীক রাদিয়াল্লাহু আনহু মদীনায় হিজরতের সময় তিন রাত লুকিয়েছিলেন, এবং সেখানে আয়াত নাযিল হয় ﴿ثَانِيَ اثْنَيْنِ إِذْ هُمَا فِي الْغَارِ﴾।",
      "howToVisit": "আরোহণের যাত্রা কঠিন পাহাড়ি পথ দিয়ে যাওয়া-আসা মিলিয়ে ৩ থেকে ৪ ঘণ্টা সময় নেয়, এবং ভালো শারীরিক সুস্থতা এবং আরোহণের জন্য উপযুক্ত জুতা প্রয়োজন।",
      "bestTime": "সূর্যোদয়ের আগে অতিরিক্ত গরম এড়াতে এবং চূড়া থেকে সূর্যাস্তের দৃশ্য দেখতে।"
    },
    "a3": {
      "name": "মসজিদে জিরানা",
      "city": "মক্কা মুকাররামা",
      "description": "যে মীকাতগুলো থেকে নবী ﷺ হুনাইন যুদ্ধের পর তাঁর উমরাহর জন্য ইহরাম করেছিলেন তার একটি।",
      "tip": "আজ এটি মক্কাহবাসীদের জন্য মীকাত হিসেবে ব্যবহৃত হয় যারা নতুন উমরাহর জন্য ইহরাম করতে চান।",
      "distance": "হারাম থেকে প্রায় ২৬ কিমি",
      "history": "নবী ﷺ এখান থেকে হুনাইন যুদ্ধ থেকে ফেরার সময় গণিমত বণ্টনের পর তাঁর উমরাহর জন্য ইহরাম করেছিলেন, এবং এটি জিরানা নামকরণ হয়েছে যে স্থানে তিনি থামেছিলেন সেই স্থানের নামানুসারে।",
      "howToVisit": "মসজিদে নামাযের স্থান এবং প্রশস্ত অযুর সুবিধা আছে মুআতামিরদের স্বাগত জানাতে যারা এখান থেকে ইহরাম করতে আসেন, এবং গাড়ি বা নির্ধারিত বাসে সহজে পৌঁছানো যায়।",
      "bestTime": "দিনের যেকোনো সময়, তবে ভিড়ের সময় এড়াতে সকাল বেলা পছন্দনীয়।"
    },
    "a4": {
      "name": "মসজিদে তানয়ীম (মসজিদে আয়েশা)",
      "city": "মক্কা মুকাররামা",
      "description": "হারামের সবচেয়ে নিকটবর্তী মীকাত, এবং এখান থেকে উম্মুল মুমিনীন আয়েশা রাদিয়াল্লাহু আনহা নবী ﷺ-এর নির্দেশে ইহরাম করেছিলেন।",
      "tip": "মক্কাহবাসী এবং স্থায়ী বাসিন্দাদের জন্য সবচেয়ে বেশি ব্যবহৃত মীকাত যারা অতিরিক্ত উমরাহ করতে চান।",
      "distance": "হারাম থেকে প্রায় ৭ কিমি",
      "history": "এটি মসজিদে আয়েশা নামে পরিচিত কারণ নবী ﷺ আব্দুর রহমান ইবনে আবী বকরকে তাঁর বোন আয়েশা রাদিয়াল্লাহু আনহাকে বিদায় হজের পর এই স্থান থেকে উমরাহ করাতে নির্দেশ দিয়েছিলেন।",
      "howToVisit": "মসজিদ প্রশস্ত পার্কিং এবং ইহরাম সহজ করার জন্য সুবিধা দিয়ে সজ্জিত, এবং প্রতিদিন হাজার হাজার মুআতামির এখানে আসেন বিশেষ করে মৌসুমে।",
      "bestTime": "রমাদান এবং হজ মৌসুমের মতো ভিড়ের মৌসুমে সন্ধ্যার ভিড়ের সময় এড়ানো পছন্দনীয়।"
    },
    "a5": {
      "name": "হারামাইন শরীফাইন জাদুঘর",
      "city": "মক্কা মুকাররামা",
      "description": "একটি জাদুঘর যা যুগ যুগ ধরে হারামাইন শরীফাইনের নির্মাণের ইতিহাস এবং পাণ্ডুলিপি এবং কাবার গিলাফ প্রদর্শন করে।",
      "tip": "মসজিদুল হারাম এবং এর ধারাবাহিক সম্প্রসারণের ইতিহাস বোঝার জন্য একটি দরকারী সাংস্কৃতিক পরিদর্শন।",
      "distance": "মসজিদুল হারামের পাশে",
      "history": "জাদুঘর নবী যুগ থেকে আধুনিক সৌদি সম্প্রসারণ পর্যন্ত হারামাইন শরীফাইনের নির্মাণের ধাপগুলো নথিবদ্ধ করে, এবং কাবার গিলাফ এবং এর পুরানো দরজার দুর্লভ ঐতিহাসিক টুকরা রয়েছে।",
      "howToVisit": "প্রবেশ সাধারণত বিনামূল্যে, এবং এতে ঘোরাফেরায় এক থেকে দুই ঘণ্টা সময় লাগে, এবং এটি পরিবারের সকল সদস্যের জন্য উপযুক্ত।",
      "bestTime": "ফজরের নামাযের পর বা নামাযের মধ্যবর্তী সময়ে যখন হারাম কম ভিড় থাকে।"
    },
    "a6": {
      "name": "মসজিদে নববী শরীফ",
      "city": "মদীনা মুনাওওয়ারা",
      "description": "দ্বিতীয় হারামাইন শরীফাইন, এবং এতে রাওদায়ে শরীফ এবং নবী ﷺ-এর কবর রয়েছে।",
      "tip": "রাওদায়ে শরীফে নামায পড়া এবং নবী ﷺ এবং তাঁর দুই সাহাবীর কবর সালাম দিয়ে যিয়ারত করা মুস্তাহাব, কবর স্পর্শ বা তাওয়াফ ছাড়াই।",
      "distance": "মদীনা মুনাওওয়ারার কেন্দ্র",
      "history": "নবী ﷺ নিজে তাঁর মদীনায় হিজরতের সময় এটি নির্মাণ করেছিলেন, এবং যুগ যুগ ধরে প্রসারিত হয়ে একটি স্থাপত্য কীর্তি হয়ে উঠেছে যাতে রাওদায়ে শরীফ রয়েছে যার সম্পর্কে ﷺ বলেছেন: «ما بين بيتي ومنبري روضة من رياض الجنة»।",
      "howToVisit": "রাওদায়ে শরীফ পরিদর্শনের জন্য নুসুক অ্যাপের মাধ্যমে বুকিং করা হয় সংগঠনের জন্য, এবং পরিদর্শনের আদব যেমন শান্ত এবং প্রশান্তি এবং ভিড় না করা মেনে চলতে হয়।",
      "bestTime": "ফজরের নামাযের পরপরই বা এশার পরে যখন ভিড় তুলনামূলকভাবে কম থাকে।"
    },
    "a7": {
      "name": "মসজিদে কুবা",
      "city": "মদীনা মুনাওওয়ারা",
      "description": "ইসলামে নির্মিত প্রথম মসজিদ, এবং নবী ﷺ প্রতি শনিবার সওয়ার হয়ে এবং পায়ে হেঁটে এখানে আসতেন।",
      "tip": "সুন্নাত হলো এখানে দুই রাকাত নামায পড়া; কারণ প্রমাণিত আছে যে এখানে নামাযের সওয়াব একটি উমরাহর সওয়াবের মতো।",
      "distance": "মসজিদে নববী থেকে প্রায় ৫ কিমি",
      "history": "ইসলামের ইতিহাসে তাকওয়ার উপর ভিত্তি করে নির্মিত প্রথম মসজিদ, নবী ﷺ হিজরত করে কুবায় পৌঁছার পরপরই এটি নির্মাণ করেছিলেন, এবং নিজের শরীফ হাত দিয়ে এর নির্মাণে অংশগ্রহণ করেছিলেন।",
      "howToVisit": "মসজিদে নববী থেকে নির্ধারিত বাস বা ট্যাক্সি দিয়ে সহজে পৌঁছানো যায়, এবং এটি বিপুল সংখ্যক নামাযী ধারণ করতে পারে।",
      "bestTime": "নবী ﷺ-এর কর্ম অনুসরণ করে শনিবার যিনি প্রতি শনিবার সওয়ার হয়ে এবং পায়ে হেঁটে এখানে যেতেন।"
    },
    "a8": {
      "name": "মসজিদে কিবলাতাইন",
      "city": "মদীনা মুনাওওয়ারা",
      "description": "যে মসজিদে মুসলিমরা নামাযের মধ্যে বাইতুল মাকদিস থেকে কাবা শরীফের দিকে ফিরেছিলেন।",
      "tip": "একটি গুরুত্বপূর্ণ ঐতিহাসিক স্থাপনা যা হিজরতের দ্বিতীয় বছরে কিবলা পরিবর্তনের ঘটনা ব্যাখ্যা করে।",
      "distance": "মসজিদে নববী থেকে প্রায় ৪ কিমি",
      "history": "নবী ﷺ এই মসজিদে তাঁর সাহাবীদের নিয়ে জোহরের নামায পড়ছিলেন, তখন তাঁর কাছে ওহী আসে বাইতুল মাকদিস থেকে কাবা শরীফের দিকে ফেরার, তাই তিনি তাঁর নামাযে ঘুরলেন এবং তাঁর পিছনের নামাযীরাও।",
      "howToVisit": "মসজিদে দুইটি স্পষ্ট কিবলা আছে যা ঐতিহাসিক ঘটনা প্রতিফলিত করে, এবং এটি মদীনা মুনাওওয়ারা দর্শনার্থীদের একটি সাধারণ গন্তব্য।",
      "bestTime": "দিনের যেকোনো সময়, তবে চিন্তা এবং ছবি তোলার জন্য পর্যাপ্ত সময় নিতে সরাসরি নামাযের সময় এড়ানো পছন্দনীয়।"
    },
    "a9": {
      "name": "জাবালে উহুদ এবং শহীদদের কবরস্থান",
      "city": "মদীনা মুনাওওয়ারা",
      "description": "বিখ্যাত উহুদ যুদ্ধের স্থান, এবং এতে যুদ্ধের শহীদদের কবরস্থান আছে যার প্রধান হলেন হামযা ইবনে আব্দুল মুত্তালিব রাদিয়াল্লাহু আনহু।",
      "tip": "শহীদদের সালাম দেওয়া এবং তাদের জন্য দুআ করা মুস্তাহাব, কবর স্পর্শ বা বরকত নেওয়া ছাড়াই।",
      "distance": "মসজিদে নববী থেকে প্রায় ৫ কিমি",
      "history": "জাবালে উহুদ মুসলিমদের সবচেয়ে বড় যুদ্ধগুলোর একটি প্রত্যক্ষ করেছে, এবং এতে সত্তর জন সাহাবী শহীদ হন যার প্রধান সাইয়্যিদুশ শুহাদা হামযা ইবনে আব্দুল মুত্তালিব রাদিয়াল্লাহু আনহু।",
      "howToVisit": "পাহাড়ের পাদদেশে এবং তার পাশের শহীদদের কবরস্থানে দাঁড়ানো যায়, কবর যিয়ারতের আদব মেনে দুআ এবং সালাম দিয়ে উচ্চস্বরে না বলে।",
      "bestTime": "আসর বা মাগরিবের আগে যখন তাপমাত্রা শীতল হয়।"
    },
    "a10": {
      "name": "বাকী",
      "city": "মদীনা মুনাওওয়ারা",
      "description": "মদীনাহবাসীদের কবরস্থান যেখানে অনেক সাহাবী এবং নবী ﷺ-এর পরিবার দাফন করা হয়েছে।",
      "tip": "এটি পরিদর্শন করা এবং এর অধিবাসীদের সালাম দেওয়া এবং তাদের জন্য ক্ষমা প্রার্থনা করা মুস্তাহাব, যেমন নবী ﷺ করতেন।",
      "distance": "মসজিদে নববীর সাথে লাগোয়া",
      "history": "বাকীতে অনেক সাহাবী এবং নবী ﷺ-এর পরিবার দাফন করা হয়েছে, এবং তিনি সাল্লাল্লাহু আলাইহি ওয়া সাল্লাম এটি পরিদর্শন করতেন এবং এর অধিবাসীদের জন্য ক্ষমা এবং রহমতের জন্য দুআ করতেন।",
      "howToVisit": "প্রবেশ নির্দিষ্ট সময়ে সীমাবদ্ধ এবং সাধারণত পুরুষদের জন্য মহিলাদের ছাড়া, এবং পরিদর্শনের সময় শান্ত এবং মর্যাদা মেনে চলতে হয়।",
      "bestTime": "ফজরের নামাযের পর যখন এর দরজা সাধারণত অল্প সময়ের জন্য খোলা হয়।"
    }
  }
}
